zdppy_password_hash/__init__.py
zdppy_password_hash/_data/wordsets/bip39.txt
zdppy_password_hash/_data/wordsets/eff_long.txt
zdppy_password_hash/_data/wordsets/eff_prefixed.txt
zdppy_password_hash/_data/wordsets/eff_short.txt
zdppy_password_hash/_setup/__init__.py
zdppy_password_hash/_setup/stamp.py
zdppy_password_hash/apache.py
zdppy_password_hash/apps.py
zdppy_password_hash/context.py
zdppy_password_hash/crypto/__init__.py
zdppy_password_hash/crypto/_blowfish/__init__.py
zdppy_password_hash/crypto/_blowfish/_gen_files.py
zdppy_password_hash/crypto/_blowfish/base.py
zdppy_password_hash/crypto/_blowfish/unrolled.py
zdppy_password_hash/crypto/_md4.py
zdppy_password_hash/crypto/des.py
zdppy_password_hash/crypto/digest.py
zdppy_password_hash/crypto/scrypt/__init__.py
zdppy_password_hash/crypto/scrypt/_builtin.py
zdppy_password_hash/crypto/scrypt/_gen_files.py
zdppy_password_hash/crypto/scrypt/_salsa.py
zdppy_password_hash/exc.py
zdppy_password_hash/ext/__init__.py
zdppy_password_hash/ext/django/__init__.py
zdppy_password_hash/ext/django/models.py
zdppy_password_hash/ext/django/utils.py
zdppy_password_hash/handlers/__init__.py
zdppy_password_hash/handlers/argon2.py
zdppy_password_hash/handlers/bcrypt.py
zdppy_password_hash/handlers/cisco.py
zdppy_password_hash/handlers/des_crypt.py
zdppy_password_hash/handlers/digests.py
zdppy_password_hash/handlers/django.py
zdppy_password_hash/handlers/fshp.py
zdppy_password_hash/handlers/ldap_digests.py
zdppy_password_hash/handlers/md5_crypt.py
zdppy_password_hash/handlers/misc.py
zdppy_password_hash/handlers/mssql.py
zdppy_password_hash/handlers/mysql.py
zdppy_password_hash/handlers/oracle.py
zdppy_password_hash/handlers/pbkdf2.py
zdppy_password_hash/handlers/phpass.py
zdppy_password_hash/handlers/postgres.py
zdppy_password_hash/handlers/roundup.py
zdppy_password_hash/handlers/scram.py
zdppy_password_hash/handlers/scrypt.py
zdppy_password_hash/handlers/sha1_crypt.py
zdppy_password_hash/handlers/sha2_crypt.py
zdppy_password_hash-0.1.0.dist-info/LICENSE
zdppy_password_hash-0.1.0.dist-info/WHEEL
zdppy_password_hash-0.1.0.dist-info/METADATA
zdppy_password_hash-0.1.0.dist-info/RECORD
